flufl/lock/__init__.py
flufl/lock/_lockfile.py
flufl/lock/py.typed
flufl_lock-8.0.2.dist-info/METADATA
flufl_lock-8.0.2.dist-info/WHEEL
flufl_lock-8.0.2.dist-info/licenses/LICENSE
flufl_lock-8.0.2.dist-info/RECORD
