Metadata-Version: 2.1
Name: flufl.lock
Version: 8.0.2
Summary: NFS-safe file locking with timeouts for POSIX and Windows
Keywords: locking locks lock
Author-Email: Barry Warsaw <barry@python.org>
License: Apache-2.0
Classifier: Development Status :: 5 - Production/Stable
Classifier: Development Status :: 6 - Mature
Classifier: Intended Audience :: Developers
Classifier: License :: OSI Approved :: Apache Software License
Classifier: Operating System :: POSIX
Classifier: Operating System :: MacOS :: MacOS X
Classifier: Operating System :: Microsoft :: Windows
Classifier: Programming Language :: Python
Classifier: Programming Language :: Python :: 3
Classifier: Topic :: Software Development :: Libraries
Classifier: Topic :: Software Development :: Libraries :: Python Modules
Project-URL: Home page, https://flufllock.readthedocs.io
Project-URL: Documentation, https://flufllock.readthedocs.io
Project-URL: Source code, https://gitlab.com/warsaw/flufl.lock.git
Project-URL: Bug tracker, https://gitlab.com/warsaw/flufl.lock/issues
Requires-Python: >=3.8
Requires-Dist: atpublic
Requires-Dist: psutil
